mymra/__init__.py
mymra/mymra.py
mymra-1.5.0.2.dist-info/LICENSE.txt
mymra-1.5.0.2.dist-info/METADATA
mymra-1.5.0.2.dist-info/WHEEL
mymra-1.5.0.2.dist-info/entry_points.txt
mymra-1.5.0.2.dist-info/top_level.txt
mymra-1.5.0.2.dist-info/RECORD
